pranavsingla_stt/main.py
pranavsingla_stt-0.1.1.dist-info/METADATA
pranavsingla_stt-0.1.1.dist-info/WHEEL
pranavsingla_stt-0.1.1.dist-info/top_level.txt
pranavsingla_stt-0.1.1.dist-info/RECORD
