Metadata-Version: 2.1
Name: pranavsingla-stt
Version: 0.1.1
Summary: A speech-to-text package by Pranav Singla
Author: Pranav Singla
Author-email: monikasingla27051982@gmail.com
